_ptcsvp/__init__.py
_ptcsvp/cmdline.py
_ptcsvp/configure.py
_ptcsvp/parametrize.py
_ptcsvp/plugin.py
_ptcsvp/varname.py
_ptcsvp/version.py
pytest_csv_params/__init__.py
pytest_csv_params/decorator.py
pytest_csv_params/dialect.py
pytest_csv_params/exception.py
pytest_csv_params/plugin.py
pytest_csv_params/shortcut.py
pytest_csv_params/types.py
pytest_csv_params/warning.py
pytest_csv_params-1.3.2.dist-info/LICENSE.txt
pytest_csv_params-1.3.2.dist-info/METADATA
pytest_csv_params-1.3.2.dist-info/WHEEL
pytest_csv_params-1.3.2.dist-info/entry_points.txt
pytest_csv_params-1.3.2.dist-info/RECORD
