Metadata-Version: 2.3
Name: pytest-csv-params
Version: 1.3.2
Summary: Pytest plugin for Test Case Parametrization with CSV files
License: Copyright Juergen Edelbluth and other contributors, https://juergen.rocks/
Keywords: py.test,pytest,csv,params,parametrize,pytest-plugin,ddt,data-driven
Author: Juergen Edelbluth
Author-email: csv_params@jued.de
Requires-Python: >=3.9,<3.14
Classifier: Development Status :: 5 - Production/Stable
Classifier: Environment :: Plugins
Classifier: Environment :: Console
Classifier: Framework :: Pytest
Classifier: Intended Audience :: Developers
Classifier: License :: OSI Approved :: MIT License
Classifier: Programming Language :: Python :: 3.8
Classifier: Programming Language :: Python :: 3.9
Classifier: Programming Language :: Python :: 3.10
Classifier: Programming Language :: Python :: 3.11
Classifier: Programming Language :: Python :: 3.12
Classifier: Programming Language :: Python :: 3.13
Classifier: Topic :: Software Development :: Testing
Classifier: Topic :: Software Development :: Quality Assurance
Classifier: Operating System :: POSIX
Classifier: Operating System :: Microsoft :: Windows
Classifier: Operating System :: MacOS :: MacOS X
Classifier: Topic :: Utilities
Provides-Extra: dev
Requires-Dist: Sphinx (>=5.1.1,<6) ; extra == "dev"
Requires-Dist: attrs (>=24.2)
Requires-Dist: livereload (>=2.6.3) ; extra == "dev"
Requires-Dist: myst-parser (>=0.18.0) ; extra == "dev"
Requires-Dist: pytest (>=8.3,<9)
Requires-Dist: pytest-bandit (>=0.6.1) ; extra == "dev"
Requires-Dist: pytest-black (>=0.3.12) ; extra == "dev"
Requires-Dist: pytest-clarity (>=1.0.1) ; extra == "dev"
Requires-Dist: pytest-cov (>=4.1) ; extra == "dev"
Requires-Dist: pytest-isort (>=3.0) ; extra == "dev"
Requires-Dist: pytest-mock (>=3.8.2) ; extra == "dev"
Requires-Dist: pytest-order (>=1.0.1,<2) ; extra == "dev"
Requires-Dist: sphinx-autodoc-typehints (>=1.19.2,<2) ; extra == "dev"
Requires-Dist: sphinx-material (>=0.0.35) ; extra == "dev"
Requires-Dist: tomli (>=2.0.1) ; extra == "dev"
Requires-Dist: tox (>=3.25.1,<4) ; extra == "dev"
Requires-Dist: tox-poetry (>=0.4.1) ; extra == "dev"
Project-URL: Changelog, https://docs.codebau.dev/pytest-plugins/pytest-csv-params/pages/changelog.html
Project-URL: Documentation, https://docs.codebau.dev/pytest-plugins/pytest-csv-params/
Project-URL: Homepage, https://git.codebau.dev/pytest-plugins/pytest-csv-params
Project-URL: Issue Tracker, https://git.codebau.dev/pytest-plugins/pytest-csv-params/issues
Project-URL: Repository, https://git.codebau.dev/pytest-plugins/pytest-csv-params
Project-URL: Releases, https://git.codebau.dev/pytest-plugins/pytest-csv-params/releases
Project-URL: Wiki, https://git.codebau.dev/pytest-plugins/pytest-csv-params/wiki
